tableauhyperio/__init__.py
tableauhyperio/tableauhyperio.py
tableauhyperio-0.8.2.dist-info/LICENSE
tableauhyperio-0.8.2.dist-info/WHEEL
tableauhyperio-0.8.2.dist-info/METADATA
tableauhyperio-0.8.2.dist-info/RECORD
