Metadata-Version: 2.1
Name: tableauhyperio
Version: 0.8.2
Summary: Read and write Tableau hyper files using Pandas DataFrames
Home-page: https://github.com/AlexFrid/tableauhyperio
License: BSD-3-Clause
Keywords: Tableau,hyper,extract,pandas,DataFrame
Author: Alexander Fridriksson
Author-email: post@alexanderfridriksson.com
Requires-Python: >=3.7.1
Classifier: Intended Audience :: Developers
Classifier: License :: OSI Approved :: BSD License
Classifier: Programming Language :: Python :: 3
Classifier: Programming Language :: Python :: 3.10
Classifier: Programming Language :: Python :: 3.8
Classifier: Programming Language :: Python :: 3.9
Classifier: Topic :: Office/Business
Classifier: Topic :: Software Development :: Libraries :: Python Modules
Requires-Dist: black (>=19.10b0)
Requires-Dist: flake8 (>=3.8.3)
Requires-Dist: pandas (>=1.0.4)
Requires-Dist: tableauhyperapi (>=0.0.10899)
Requires-Dist: tqdm (>=4.46.1)
Project-URL: Repository, https://github.com/AlexFrid/tableauhyperio
